{
  "binder-transaction-too-large": {
    "demotions": [],
    "evidence_context": {},
    "fail_count": 0,
    "id": "binder-transaction-too-large",
    "leak_check": "",
    "lineage": "authored cold-start",
    "measured_lift": {},
    "tier": "candidate",
    "validating_case_ids": []
  },
  "camera-gl-surface-lifecycle": {
    "demotions": [],
    "evidence_context": {},
    "fail_count": 0,
    "id": "camera-gl-surface-lifecycle",
    "leak_check": "",
    "lineage": "authored cold-start",
    "measured_lift": {},
    "tier": "candidate",
    "validating_case_ids": []
  },
  "foreground-service-not-started": {
    "demotions": [],
    "evidence_context": {},
    "fail_count": 0,
    "id": "foreground-service-not-started",
    "leak_check": "",
    "lineage": "authored cold-start",
    "measured_lift": {},
    "tier": "candidate",
    "validating_case_ids": []
  },
  "fragment-view-after-destroy-npe": {
    "demotions": [],
    "evidence_context": {},
    "fail_count": 0,
    "id": "fragment-view-after-destroy-npe",
    "leak_check": "",
    "lineage": "authored cold-start",
    "measured_lift": {},
    "tier": "candidate",
    "validating_case_ids": []
  },
  "illegalstate-after-savedinstancestate": {
    "demotions": [],
    "evidence_context": {},
    "fail_count": 0,
    "id": "illegalstate-after-savedinstancestate",
    "leak_check": "",
    "lineage": "authored cold-start",
    "measured_lift": {},
    "tier": "candidate",
    "validating_case_ids": []
  },
  "main-thread-blocking-anr": {
    "demotions": [],
    "evidence_context": {},
    "fail_count": 0,
    "id": "main-thread-blocking-anr",
    "leak_check": "",
    "lineage": "authored cold-start",
    "measured_lift": {},
    "tier": "candidate",
    "validating_case_ids": []
  },
  "media-player-illegal-state": {
    "demotions": [],
    "evidence_context": {},
    "fail_count": 0,
    "id": "media-player-illegal-state",
    "leak_check": "",
    "lineage": "authored cold-start",
    "measured_lift": {},
    "tier": "candidate",
    "validating_case_ids": []
  },
  "native-heap-corruption-abort": {
    "demotions": [],
    "evidence_context": {},
    "fail_count": 0,
    "id": "native-heap-corruption-abort",
    "leak_check": "",
    "lineage": "authored cold-start",
    "measured_lift": {},
    "tier": "candidate",
    "validating_case_ids": []
  },
  "native-lib-load-failure": {
    "demotions": [],
    "evidence_context": {},
    "fail_count": 0,
    "id": "native-lib-load-failure",
    "leak_check": "",
    "lineage": "authored cold-start",
    "measured_lift": {},
    "tier": "candidate",
    "validating_case_ids": []
  },
  "native-null-deref-segv": {
    "demotions": [],
    "evidence_context": {},
    "fail_count": 0,
    "id": "native-null-deref-segv",
    "leak_check": "",
    "lineage": "authored cold-start",
    "measured_lift": {},
    "tier": "candidate",
    "validating_case_ids": []
  },
  "realtime-audio-callback-underrun": {
    "demotions": [],
    "evidence_context": {},
    "fail_count": 0,
    "id": "realtime-audio-callback-underrun",
    "leak_check": "",
    "lineage": "authored cold-start",
    "measured_lift": {},
    "tier": "candidate",
    "validating_case_ids": []
  },
  "shared-state-race-cme": {
    "demotions": [],
    "evidence_context": {},
    "fail_count": 0,
    "id": "shared-state-race-cme",
    "leak_check": "",
    "lineage": "authored cold-start",
    "measured_lift": {},
    "tier": "candidate",
    "validating_case_ids": []
  }
}
